{"assets/background.jpg":["assets/background.jpg"],"assets/bg_about.png":["assets/bg_about.png"],"assets/bg_home.png":["assets/bg_home.png"],"assets/logo.jpeg":["assets/logo.jpeg"],"assets/main_background.webp":["assets/main_background.webp"],"assets/main_background_2.webp":["assets/main_background_2.webp"],"assets/main_background_3.webp":["assets/main_background_3.webp"],"assets/pd1.jpeg":["assets/pd1.jpeg"],"assets/pd10.jpeg":["assets/pd10.jpeg"],"assets/pd11.jpeg":["assets/pd11.jpeg"],"assets/pd12.jpeg":["assets/pd12.jpeg"],"assets/pd13.jpeg":["assets/pd13.jpeg"],"assets/pd14.jpeg":["assets/pd14.jpeg"],"assets/pd15.jpeg":["assets/pd15.jpeg"],"assets/pd16.jpeg":["assets/pd16.jpeg"],"assets/pd17.jpeg":["assets/pd17.jpeg"],"assets/pd18.jpeg":["assets/pd18.jpeg"],"assets/pd19.jpeg":["assets/pd19.jpeg"],"assets/pd2.jpeg":["assets/pd2.jpeg"],"assets/pd20.jpeg":["assets/pd20.jpeg"],"assets/pd21.jpeg":["assets/pd21.jpeg"],"assets/pd22.jpeg":["assets/pd22.jpeg"],"assets/pd23.jpeg":["assets/pd23.jpeg"],"assets/pd24.jpeg":["assets/pd24.jpeg"],"assets/pd25.jpeg":["assets/pd25.jpeg"],"assets/pd3.jpeg":["assets/pd3.jpeg"],"assets/pd4.jpeg":["assets/pd4.jpeg"],"assets/pd5.jpeg":["assets/pd5.jpeg"],"assets/pd6.jpeg":["assets/pd6.jpeg"],"assets/pd7.jpeg":["assets/pd7.jpeg"],"assets/pd8.jpeg":["assets/pd8.jpeg"],"assets/pd9.jpeg":["assets/pd9.jpeg"],"assets/product_investment_cast.png":["assets/product_investment_cast.png"],"assets/product_sand_cast.png":["assets/product_sand_cast.png"],"assets/product_shell_mold_cast.png":["assets/product_shell_mold_cast.png"],"fonts/Electrolize-Regular.ttf":["fonts/Electrolize-Regular.ttf"],"fonts/Montserrat-Regular.ttf":["fonts/Montserrat-Regular.ttf"],"packages/cupertino_icons/assets/CupertinoIcons.ttf":["packages/cupertino_icons/assets/CupertinoIcons.ttf"]}